setup.py
serve_secrets/__init__.py
serve_secrets/main.py
serve_secrets.egg-info/PKG-INFO
serve_secrets.egg-info/SOURCES.txt
serve_secrets.egg-info/dependency_links.txt
serve_secrets.egg-info/entry_points.txt
serve_secrets.egg-info/requires.txt
serve_secrets.egg-info/top_level.txt