Metadata-Version: 2.2
Name: serve_secrets
Version: 1.5.0
Summary: A tool to store and retrieve API keys using the system's password manager.
Home-page: https://github.com/samanvaya/serve_secrets
Author: Samanvay Yagsen
Author-email: samanvaya.yagsen@gmail.com
Classifier: Programming Language :: Python :: 3
Classifier: License :: OSI Approved :: MIT License
Classifier: Operating System :: OS Independent
Requires-Python: >=3.6
Requires-Dist: keyring
Requires-Dist: pyperclip
Dynamic: author
Dynamic: author-email
Dynamic: classifier
Dynamic: home-page
Dynamic: requires-dist
Dynamic: requires-python
Dynamic: summary
